{"2017-09-23 pmCBM":{"status":"Success","type":"CBM","info":"Central Bank of Myanmar","description":"Official Website of Central Bank of Myanmar","timestamp":"1506067200","rates":{"USD":"1,360.0","VND":"5.9832","PHP":"26.688","KRW":"119.92","HKD":"174.22","BRL":"434.25","RSD":"13.692","MYR":"323.96","CAD":"1,103.2","GBP":"1,846.1","SEK":"170.80","NOK":"174.09","ILS":"387.71","AUD":"1,077.1","DKK":"218.86","RUB":"23.436","KWD":"4,513.1","INR":"20.984","BND":"1,007.8","EUR":"1,624.1","NPR":"13.211","ZAR":"102.31","CNY":"206.37","CHF":"1,402.0","THB":"41.063","PKR":"12.909","KES":"13.160","BDT":"16.590","EGP":"77.074","SAR":"362.65","LAK":"16.421","IDR":"10.240","KHR":"33.512","SGD":"1,007.0","LKR":"8.8848","NZD":"991.25","CZK":"62.392","JPY":"1,210.6"}}}